<?xml version="1.0"?>
<runHistory script="DYmanic">
 <run>
  <RunDate>2017-01-13 14:27:16.571 -0700</RunDate>
  <Status>Success</Status>
  <Duration>0.515060</Duration>
  <Errors>0</Errors>
  <Warnings>0</Warnings>
  <Exceptions>0</Exceptions>
  <Successes>1</Successes>
  <LogFile>20170113_142716.571/LogFile.txt</LogFile>
  <ReturnValue></ReturnValue>
  <ErrorMessage></ErrorMessage>
 </run>
 <run>
  <RunDate>2017-01-13 14:27:25.653 -0700</RunDate>
  <Status>Success</Status>
  <Duration>0.488862</Duration>
  <Errors>0</Errors>
  <Warnings>0</Warnings>
  <Exceptions>0</Exceptions>
  <Successes>1</Successes>
  <LogFile>20170113_142725.653/LogFile.txt</LogFile>
  <ReturnValue></ReturnValue>
  <ErrorMessage></ErrorMessage>
 </run>
 <run>
  <RunDate>2017-01-13 14:29:05.455 -0700</RunDate>
  <Status>Success</Status>
  <Duration>1.611296</Duration>
  <Errors>0</Errors>
  <Warnings>0</Warnings>
  <Exceptions>0</Exceptions>
  <Successes>1</Successes>
  <LogFile>20170113_142905.455/LogFile.txt</LogFile>
  <ReturnValue></ReturnValue>
  <ErrorMessage></ErrorMessage>
 </run>
 <run>
  <RunDate>2017-01-13 14:29:12.555 -0700</RunDate>
  <Status>Success</Status>
  <Duration>1.570501</Duration>
  <Errors>0</Errors>
  <Warnings>0</Warnings>
  <Exceptions>0</Exceptions>
  <Successes>1</Successes>
  <LogFile>20170113_142912.555/LogFile.txt</LogFile>
  <ReturnValue></ReturnValue>
  <ErrorMessage></ErrorMessage>
 </run>
 <run>
  <RunDate>2017-01-13 14:29:26.125 -0700</RunDate>
  <Status>Success</Status>
  <Duration>1.567734</Duration>
  <Errors>0</Errors>
  <Warnings>0</Warnings>
  <Exceptions>0</Exceptions>
  <Successes>1</Successes>
  <LogFile>20170113_142926.125/LogFile.txt</LogFile>
  <ReturnValue></ReturnValue>
  <ErrorMessage></ErrorMessage>
 </run>
 <run>
  <RunDate>2017-01-13 14:29:47.027 -0700</RunDate>
  <Status>Success</Status>
  <Duration>1.608563</Duration>
  <Errors>0</Errors>
  <Warnings>0</Warnings>
  <Exceptions>0</Exceptions>
  <Successes>1</Successes>
  <LogFile>20170113_142947.027/LogFile.txt</LogFile>
  <ReturnValue></ReturnValue>
  <ErrorMessage></ErrorMessage>
 </run>
 <run>
  <RunDate>2017-01-13 14:30:02.763 -0700</RunDate>
  <Status>Success</Status>
  <Duration>3.814217</Duration>
  <Errors>0</Errors>
  <Warnings>0</Warnings>
  <Exceptions>0</Exceptions>
  <Successes>1</Successes>
  <LogFile>20170113_143002.763/LogFile.txt</LogFile>
  <ReturnValue></ReturnValue>
  <ErrorMessage></ErrorMessage>
 </run>
</runHistory>
